README.md
pypi.py
easily.egg-info/PKG-INFO
easily.egg-info/SOURCES.txt
easily.egg-info/dependency_links.txt
easily.egg-info/top_level.txt