Metadata-Version: 1.2
Name: easily
Version: 0.0.1a0
Summary: easily
Home-page: https://github.com/mattian7741/easily
Author: Matthew Hansen
Author-email: easily@mattian.com
License: MIT
Download-URL: https://github.com/mattian7741/easily/archive/v0.0.01-alpha.tar.gz
Platform: UNKNOWN
Classifier: Development Status :: 3 - Alpha
Classifier: Intended Audience :: Developers
Classifier: Topic :: Software Development :: Build Tools
Classifier: License :: OSI Approved :: MIT License
Classifier: Programming Language :: Python :: 3
Classifier: Programming Language :: Python :: 3.4
Classifier: Programming Language :: Python :: 3.5
Classifier: Programming Language :: Python :: 3.6
Requires-Python: >=3
